LICENSE
MANIFEST.in
README.md
pyproject.toml
setup.py
src/cykhash/__init__.py
src/cykhash/common.pxi
src/cykhash/compat.py
src/cykhash/floatdef.pxd
src/cykhash/hash_functions.pxi
src/cykhash/khash.pxi
src/cykhash/khashmaps.pxd
src/cykhash/khashmaps.pyx
src/cykhash/khashsets.pxd
src/cykhash/khashsets.pyx
src/cykhash/memory.pxi
src/cykhash/murmurhash.pxi
src/cykhash/unique.pxd
src/cykhash/unique.pyx
src/cykhash/utils.pyx
src/cykhash.egg-info/PKG-INFO
src/cykhash.egg-info/SOURCES.txt
src/cykhash.egg-info/dependency_links.txt
src/cykhash.egg-info/not-zip-safe
src/cykhash.egg-info/top_level.txt
src/cykhash/maps/map_header.pxi
src/cykhash/maps/map_header.pxi.in
src/cykhash/maps/map_impl.pxi
src/cykhash/maps/map_impl.pxi.in
src/cykhash/maps/map_init.pxi
src/cykhash/maps/map_init.pxi.in
src/cykhash/sets/set_header.pxi
src/cykhash/sets/set_header.pxi.in
src/cykhash/sets/set_impl.pxi
src/cykhash/sets/set_impl.pxi.in
src/cykhash/sets/set_init.pxi
src/cykhash/sets/set_init.pxi.in
src/cykhash/unique/unique_impl.pxi
src/cykhash/unique/unique_impl.pxi.in