Metadata-Version: 2.1
Name: cykhash
Version: 2.0.1
Summary: cython wrapper for khash-sets/maps, efficient implementation of isin and unique
Home-page: https://github.com/realead/cykhash
Author: Egor Dranischnikow
License: MIT
Platform: UNKNOWN
Classifier: Programming Language :: Python :: 3
License-File: LICENSE
